{
  "devices": {
    "1": {
      "name": "Strip lamp",
      "code": 64704186
    },
    "2": {
      "name": "Strip lamp",
      "code": 8191049
    },
    "3": {
      "name": "Table lamp",
      "code": 49147702
    },
    "4": {
      "name": "Table lamp (Elsa)",
      "code": 20297017
    },
    "5": {
      "name": "Table lamp (Sam)",
      "code": 58271973
    },
    "6": {
      "name": "Table lamp",
      "code": 54433899
    }
  },
  "rooms": {
    "1": {
      "name": "Corridor",
      "device_ids": [
        "1"
      ]
    },
    "2": {
      "name": "Living room",
      "device_ids": [
        "2",
        "3"
      ]
    },
    "3": {
      "name": "Bed room",
      "device_ids": [
        "4",
        "5"
      ]
    },
    "4": {
      "name": "Office room",
      "device_ids": [
        "6"
      ]
    }
  }
}